{"version":3, "nodes":[{"id":"471205AF-0BA0-42D0-B600-9DA02CAA2630", "lastModified":"2016-04-12T12:24:39.302+03:00", "name":"AddressBook", "type":"Project"},{"id":"B43A57DB-A51C-42DC-9260-7076E131FF51", "lastModified":"2016-03-30T19:11:48.549+03:00", "name":"Accounts", "type":"Service", "parentId":"471205AF-0BA0-42D0-B600-9DA02CAA2630"},{"id":"DF846C45-B82D-4180-9CD9-F26D220A108B", "lastModified":"2016-04-06T16:29:05.683+03:00", "name":"AttributeGroups", "type":"Service", "parentId":"471205AF-0BA0-42D0-B600-9DA02CAA2630"},{"id":"D401C708-9EF8-4204-80FA-1F11E071F8B4", "lastModified":"2016-04-06T00:45:59.179+03:00", "name":"AttributeTypes", "type":"Service", "parentId":"471205AF-0BA0-42D0-B600-9DA02CAA2630"},{"id":"24189D6F-FD2C-49FB-8833-18B8AE854DE2", "lastModified":"2016-04-02T21:49:51.196+03:00", "name":"Attributes", "type":"Service", "parentId":"471205AF-0BA0-42D0-B600-9DA02CAA2630"},{"id":"F7165F8B-221B-4B45-B55E-7DDBAFCF1908", "lastModified":"2016-04-12T11:27:05.123+03:00", "name":"Contacts", "type":"Service", "parentId":"471205AF-0BA0-42D0-B600-9DA02CAA2630"},{"id":"AD727C77-C632-4F8B-915B-D96A4FFDCBC6", "lastModified":"2016-04-03T16:13:38.302+03:00", "name":"FieldTypes", "type":"Service", "parentId":"471205AF-0BA0-42D0-B600-9DA02CAA2630"},{"id":"6F0D603A-0EE4-44C8-ADB9-66EFA5ECD7FF", "lastModified":"2016-04-12T12:24:39.304+03:00", "name":"Notes", "type":"Service", "parentId":"471205AF-0BA0-42D0-B600-9DA02CAA2630"},{"id":"7B6D9782-182B-4D95-84D9-7E8304262F77", "lastModified":"2016-03-30T19:18:24.675+03:00", "name":"Permissions", "type":"Service", "parentId":"471205AF-0BA0-42D0-B600-9DA02CAA2630"},{"id":"55472F2F-E41F-4A8A-8814-1AF4D6CFAEE5", "lastModified":"2016-03-30T19:18:54.574+03:00", "name":"Roles", "type":"Service", "parentId":"471205AF-0BA0-42D0-B600-9DA02CAA2630"},{"id":"16087174-6DB1-4B0C-8CEC-749D79440158", "lastModified":"2016-04-12T12:00:27.568+03:00", "name":"Tags", "type":"Service", "parentId":"471205AF-0BA0-42D0-B600-9DA02CAA2630"},{"id":"9E23650C-0AF1-46AC-BB73-298F906D1008", "lastModified":"2016-03-28T11:41:02.313+03:00", "name":"Test", "type":"Service", "parentId":"471205AF-0BA0-42D0-B600-9DA02CAA2630"},{"id":"6A685804-264A-45FA-9932-691E9313130F", "lastModified":"2016-03-26T16:45:53.503+03:00", "name":"account", "type":"Service", "parentId":"471205AF-0BA0-42D0-B600-9DA02CAA2630"},{"uriEditor":true, "id":"907B370B-D07A-453D-9809-1E63D75AEA47", "lastModified":"2016-03-28T11:45:07.240+03:00", "name":"Authenticate user", "headers":[{"enabled":true, "name":"Content-Type", "value":"application/json"}], "type":"Request", "method":{"requestBody":true, "link":"http://tools.ietf.org/html/rfc7231#section-4.3.3", "name":"POST"}, "body":{"autoSetLength":true, "textBody":"{\n  \"email\":\"test@test.com\",\n  \"password\":\"passwd\"\n}", "bodyType":"Text"}, "headersType":"Form", "uri":{"path":"localhost:8080/addressbook/rest/authenticateUser", "scheme":{"name":"http", "version":"V11"}}, "parentId":"471205AF-0BA0-42D0-B600-9DA02CAA2630"},{"uriEditor":true, "id":"F5B96F43-5409-4AF8-9861-1ED8148B73AD", "lastModified":"2016-03-30T19:10:01.450+03:00", "name":"Create (POST)", "headers":[{"enabled":true, "name":"Content-Type", "value":"application/json"}], "type":"Request", "method":{"requestBody":true, "link":"http://tools.ietf.org/html/rfc7231#section-4.3.3", "name":"POST"}, "body":{"autoSetLength":true, "textBody":"{\n  \"email\":\"admin@test\",\n  \"password\":\"passwd\"\n}", "bodyType":"Text"}, "headersType":"Form", "uri":{"path":"localhost:8080/addressbook/rest/accounts", "query":{"delimiter":"&", "items":[]}, "scheme":{"name":"http", "version":"V11"}}, "parentId":"B43A57DB-A51C-42DC-9260-7076E131FF51"},{"uriEditor":true, "id":"6D3EA628-A7E3-4628-B3DA-0CAA52827AA3", "lastModified":"2016-03-30T19:08:51.309+03:00", "name":"Delete (DELETE)", "headers":[], "type":"Request", "method":{"link":"http://tools.ietf.org/html/rfc7231#section-4.3.5", "name":"DELETE"}, "body":{"autoSetLength":true, "bodyType":"Text"}, "headersType":"Form", "uri":{"path":"localhost:8080/addressbook/rest/accounts/1", "query":{"delimiter":"&", "items":[]}, "scheme":{"name":"http", "version":"V11"}}, "parentId":"B43A57DB-A51C-42DC-9260-7076E131FF51"},{"uriEditor":true, "id":"3C554760-83B4-497E-8199-F906621BA79A", "lastModified":"2016-03-28T11:39:28.752+03:00", "name":"Get accounts by role", "headers":[], "type":"Request", "method":{"link":"http://tools.ietf.org/html/rfc7231#section-4.3.1", "name":"GET"}, "body":{"autoSetLength":true, "textBody":"{\n  \"description\":\"hellotest-(post)\"\n}", "bodyType":"Text"}, "headersType":"Form", "uri":{"path":"localhost:8080/addressbook/rest/accounts/getAllByRole/", "query":{"delimiter":"&", "items":[{"enabled":true, "name":"role", "value":"User"}]}, "scheme":{"name":"http", "version":"V11"}}, "parentId":"B43A57DB-A51C-42DC-9260-7076E131FF51"},{"uriEditor":true, "id":"45ADB8B8-0BFF-4FFD-BA51-1523EFBF536D", "lastModified":"2016-03-30T19:10:44.861+03:00", "name":"Get all", "headers":[], "type":"Request", "method":{"link":"http://tools.ietf.org/html/rfc7231#section-4.3.1", "name":"GET"}, "body":{"autoSetLength":true, "bodyType":"Text"}, "headersType":"Form", "uri":{"path":"localhost:8080/addressbook/rest/accounts/get_all", "query":{"delimiter":"&", "items":[]}, "scheme":{"name":"http", "version":"V11"}}, "parentId":"B43A57DB-A51C-42DC-9260-7076E131FF51"},{"uriEditor":true, "id":"B7953342-B769-4C37-AA17-D09C5A075809", "lastModified":"2016-03-30T19:11:11.809+03:00", "name":"Read (GET)", "headers":[], "type":"Request", "method":{"link":"http://tools.ietf.org/html/rfc7231#section-4.3.1", "name":"GET"}, "body":{"autoSetLength":true, "bodyType":"Text"}, "headersType":"Form", "uri":{"path":"localhost:8080/addressbook/rest/accounts/1", "query":{"delimiter":"&", "items":[]}, "scheme":{"name":"http", "version":"V11"}}, "parentId":"B43A57DB-A51C-42DC-9260-7076E131FF51"},{"uriEditor":true, "id":"5EC5E819-B825-4139-864E-E252EA8F6F11", "lastModified":"2016-03-30T19:11:48.550+03:00", "name":"Update (PUT)", "headers":[{"enabled":true, "name":"Content-Type", "value":"application/json"}], "type":"Request", "method":{"requestBody":true, "link":"http://tools.ietf.org/html/rfc7231#section-4.3.4", "name":"PUT"}, "body":{"autoSetLength":true, "textBody":"{\n  \"email\":\"admin@test\",\n  \"password\":\"passwd\"\n}", "bodyType":"Text"}, "headersType":"Form", "uri":{"path":"localhost:8080/addressbook/rest/accounts/1", "query":{"delimiter":"&", "items":[]}, "scheme":{"name":"http", "version":"V11"}}, "parentId":"B43A57DB-A51C-42DC-9260-7076E131FF51"},{"uriEditor":true, "id":"5888F6D5-D07C-42B8-8182-9438C947CFA3", "lastModified":"2016-04-06T16:26:49.273+03:00", "name":"Create (POST)", "headers":[{"enabled":true, "name":"Content-Type", "value":"application/json"}], "type":"Request", "method":{"requestBody":true, "link":"http://tools.ietf.org/html/rfc7231#section-4.3.3", "name":"POST"}, "body":{"autoSetLength":true, "textBody":"{\n  \"name\":\"ddds\",\n  \"description\":\"ggg\"\n}", "bodyType":"Text"}, "headersType":"Form", "uri":{"path":"localhost:8080/addressbook/rest/attribute_groups", "query":{"delimiter":"&", "items":[]}, "scheme":{"name":"http", "version":"V11"}}, "parentId":"DF846C45-B82D-4180-9CD9-F26D220A108B"},{"uriEditor":true, "id":"7C1CB210-E3F2-4B06-A366-143021CF7AF7", "lastModified":"2016-03-30T19:02:54.009+03:00", "name":"Delete (DELETE)", "headers":[], "type":"Request", "method":{"link":"http://tools.ietf.org/html/rfc7231#section-4.3.5", "name":"DELETE"}, "body":{"autoSetLength":true, "bodyType":"Text"}, "headersType":"Form", "uri":{"path":"localhost:8080/addressbook/rest/attribute_groups/2", "query":{"delimiter":"&", "items":[]}, "scheme":{"name":"http", "version":"V11"}}, "parentId":"DF846C45-B82D-4180-9CD9-F26D220A108B"},{"uriEditor":true, "id":"4FF72394-7778-4B6E-AC84-67CE78C4EED6", "lastModified":"2016-03-30T19:01:20.398+03:00", "name":"Get all", "headers":[], "type":"Request", "method":{"link":"http://tools.ietf.org/html/rfc7231#section-4.3.1", "name":"GET"}, "body":{"autoSetLength":true, "bodyType":"Text"}, "headersType":"Form", "uri":{"path":"localhost:8080/addressbook/rest/attribute_groups/get_all", "query":{"delimiter":"&", "items":[]}, "scheme":{"name":"http", "version":"V11"}}, "parentId":"DF846C45-B82D-4180-9CD9-F26D220A108B"},{"uriEditor":true, "id":"FAC7864D-6F32-49EF-A752-137962568DC3", "lastModified":"2016-03-30T19:01:31.076+03:00", "name":"Read (GET)", "headers":[], "type":"Request", "method":{"link":"http://tools.ietf.org/html/rfc7231#section-4.3.1", "name":"GET"}, "body":{"autoSetLength":true, "bodyType":"Text"}, "headersType":"Form", "uri":{"path":"localhost:8080/addressbook/rest/attribute_groups/1", "query":{"delimiter":"&", "items":[]}, "scheme":{"name":"http", "version":"V11"}}, "parentId":"DF846C45-B82D-4180-9CD9-F26D220A108B"},{"uriEditor":true, "id":"084BADF2-72C9-4F52-9471-37E62FF6F752", "lastModified":"2016-04-06T16:29:05.683+03:00", "name":"Update (PUT)", "headers":[{"enabled":true, "name":"Content-Type", "value":"application/json"}], "type":"Request", "method":{"requestBody":true, "link":"http://tools.ietf.org/html/rfc7231#section-4.3.4", "name":"PUT"}, "body":{"autoSetLength":true, "textBody":"{\n  \"name\":\"dddsss\",\n  \"description\":\"ggg\"\n}", "bodyType":"Text"}, "headersType":"Form", "uri":{"path":"localhost:8080/addressbook/rest/attribute_groups/1", "query":{"delimiter":"&", "items":[]}, "scheme":{"name":"http", "version":"V11"}}, "parentId":"DF846C45-B82D-4180-9CD9-F26D220A108B"},{"uriEditor":true, "id":"6F60197E-EF11-40E6-916E-1FCC82916D98", "lastModified":"2016-04-06T00:45:59.180+03:00", "name":"Create (POST)", "headers":[{"enabled":true, "name":"Content-Type", "value":"application/json"}], "type":"Request", "method":{"requestBody":true, "link":"http://tools.ietf.org/html/rfc7231#section-4.3.3", "name":"POST"}, "body":{"autoSetLength":true, "textBody":"{\n  \"name\":\"namee\"\n}", "bodyType":"Text"}, "headersType":"Form", "uri":{"path":"localhost:8080/addressbook/rest/attribute_types", "query":{"delimiter":"&", "items":[{"enabled":true, "name":"field_type_id", "value":"1"}]}, "scheme":{"name":"http", "version":"V11"}}, "parentId":"D401C708-9EF8-4204-80FA-1F11E071F8B4"},{"uriEditor":true, "id":"82244DC1-C9A4-46D5-A263-69AB891718F1", "lastModified":"2016-04-02T22:20:52.770+03:00", "name":"Delete (DELETE)", "headers":[], "type":"Request", "method":{"link":"http://tools.ietf.org/html/rfc7231#section-4.3.5", "name":"DELETE"}, "body":{"autoSetLength":true, "bodyType":"Text"}, "headersType":"Form", "uri":{"path":"localhost:8080/addressbook/rest/attribute_types/1", "query":{"delimiter":"&", "items":[]}, "scheme":{"name":"http", "version":"V11"}}, "parentId":"D401C708-9EF8-4204-80FA-1F11E071F8B4"},{"uriEditor":true, "id":"60B6DE6E-0480-4AEA-82CE-B107CE41A6BC", "lastModified":"2016-04-02T22:14:41.629+03:00", "name":"Read (GET)", "headers":[], "type":"Request", "method":{"link":"http://tools.ietf.org/html/rfc7231#section-4.3.1", "name":"GET"}, "body":{"autoSetLength":true, "bodyType":"Text"}, "headersType":"Form", "uri":{"path":"localhost:8080/addressbook/rest/attribute_types/13", "query":{"delimiter":"&", "items":[]}, "scheme":{"name":"http", "version":"V11"}}, "parentId":"D401C708-9EF8-4204-80FA-1F11E071F8B4"},{"uriEditor":true, "id":"605BBA3F-8DC2-45E6-B3C7-ACE516AB3CFC", "lastModified":"2016-04-02T22:16:20.207+03:00", "name":"Update (PUT)", "headers":[{"enabled":true, "name":"Content-Type", "value":"application/json"}], "type":"Request", "method":{"requestBody":true, "link":"http://tools.ietf.org/html/rfc7231#section-4.3.4", "name":"PUT"}, "body":{"autoSetLength":true, "textBody":"{\n  \"name\":\"woo\"\n}", "bodyType":"Text"}, "headersType":"Form", "uri":{"path":"localhost:8080/addressbook/rest/attribute_types/13", "query":{"delimiter":"&", "items":[{"enabled":true, "name":"field_type_id", "value":"1"}]}, "scheme":{"name":"http", "version":"V11"}}, "parentId":"D401C708-9EF8-4204-80FA-1F11E071F8B4"},{"uriEditor":true, "id":"3F1BCBBD-DB86-40CC-9599-2248EB3480AB", "lastModified":"2016-04-02T16:33:17.495+03:00", "name":"Create (POST)", "headers":[{"enabled":true, "name":"Content-Type", "value":"application/json"}], "type":"Request", "method":{"requestBody":true, "link":"http://tools.ietf.org/html/rfc7231#section-4.3.3", "name":"POST"}, "body":{"autoSetLength":true, "textBody":"{\n  \"name\":\"NN\",\n  \"description\":\"DESC\"\n}", "bodyType":"Text"}, "headersType":"Form", "uri":{"path":"localhost:8080/addressbook/rest/attributes", "query":{"delimiter":"&", "items":[{"enabled":true, "name":"type_id", "value":"1"},{"enabled":true, "name":"group_id", "value":"1"}]}, "scheme":{"name":"http", "version":"V11"}}, "parentId":"24189D6F-FD2C-49FB-8833-18B8AE854DE2"},{"uriEditor":true, "id":"76FA3234-BC51-4E91-8955-57BDAC298E96", "lastModified":"2016-03-26T21:27:29.488+03:00", "name":"Delete (DELETE)", "headers":[], "type":"Request", "method":{"link":"http://tools.ietf.org/html/rfc7231#section-4.3.5", "name":"DELETE"}, "body":{"autoSetLength":true, "bodyType":"Text"}, "headersType":"Form", "uri":{"path":"localhost:8080/addressbook/rest/attributes/1", "query":{"delimiter":"&", "items":[]}, "scheme":{"name":"http", "version":"V11"}}, "parentId":"24189D6F-FD2C-49FB-8833-18B8AE854DE2"},{"uriEditor":true, "id":"19574F3C-94A5-4463-BA5B-FD98246E6C96", "lastModified":"2016-03-26T21:26:37.651+03:00", "name":"Read (GET)", "headers":[], "type":"Request", "method":{"link":"http://tools.ietf.org/html/rfc7231#section-4.3.1", "name":"GET"}, "body":{"autoSetLength":true, "bodyType":"Text"}, "headersType":"Form", "uri":{"path":"localhost:8080/addressbook/rest/attributes/1", "query":{"delimiter":"&", "items":[]}, "scheme":{"name":"http", "version":"V11"}}, "parentId":"24189D6F-FD2C-49FB-8833-18B8AE854DE2"},{"uriEditor":true, "id":"789ED743-22CB-49B5-BD63-92CD9DEF61A4", "lastModified":"2016-04-02T21:49:51.196+03:00", "name":"Update (PUT)", "headers":[{"enabled":true, "name":"Content-Type", "value":"application/json"}], "type":"Request", "method":{"requestBody":true, "link":"http://tools.ietf.org/html/rfc7231#section-4.3.4", "name":"PUT"}, "body":{"autoSetLength":true, "textBody":"{\n  \"name\":\"Updated N\",\n  \"description\":\"Updated D\"\n}", "bodyType":"Text"}, "headersType":"Form", "uri":{"path":"localhost:8080/addressbook/rest/attributes/1", "query":{"delimiter":"&", "items":[{"enabled":true, "name":"type_id", "value":"1"},{"enabled":true, "name":"group_id", "value":"1"}]}, "scheme":{"name":"http", "version":"V11"}}, "parentId":"24189D6F-FD2C-49FB-8833-18B8AE854DE2"},{"uriEditor":true, "id":"BB27CF8B-7B4D-4604-A337-DF602197CCAF", "lastModified":"2016-04-03T15:45:39.827+03:00", "name":"Create (POST)", "headers":[{"enabled":true, "name":"Content-Type", "value":"application/json"}], "type":"Request", "method":{"requestBody":true, "link":"http://tools.ietf.org/html/rfc7231#section-4.3.3", "name":"POST"}, "body":{"autoSetLength":true, "textBody":"{\n  \"firstName\":\"Ivan\",\n  \"lastName\":\"Petrov\",\n  \"description\":\"demo entry\"\n}", "bodyType":"Text"}, "headersType":"Form", "uri":{"path":"localhost:8080/addressbook/rest/contacts", "query":{"delimiter":"&", "items":[]}, "scheme":{"name":"http", "version":"V11"}}, "parentId":"F7165F8B-221B-4B45-B55E-7DDBAFCF1908"},{"uriEditor":true, "id":"3DAEB759-24BC-4861-9E47-40E49900CB9D", "lastModified":"2016-04-06T01:02:11.427+03:00", "name":"Delete (DELETE)", "headers":[], "type":"Request", "method":{"link":"http://tools.ietf.org/html/rfc7231#section-4.3.5", "name":"DELETE"}, "body":{"autoSetLength":true, "bodyType":"Text"}, "headersType":"Form", "uri":{"path":"localhost:8080/addressbook/rest/contacts/1", "query":{"delimiter":"&", "items":[]}, "scheme":{"name":"http", "version":"V11"}}, "parentId":"F7165F8B-221B-4B45-B55E-7DDBAFCF1908"},{"uriEditor":true, "id":"93D6637E-9618-4A81-B8C3-0E82DF142D6E", "lastModified":"2016-04-12T11:25:36.473+03:00", "name":"Get all by account (GET)", "headers":[{"enabled":true, "name":"Content-Type", "value":"application/json"}], "type":"Request", "method":{"link":"http://tools.ietf.org/html/rfc7231#section-4.3.1", "name":"GET"}, "body":{"autoSetLength":true, "textBody":"{\n  \"firstName\":\"Ivan\",\n  \"lastName\":\"Petrov\",\n  \"description\":\"demo entry\"\n}", "bodyType":"Text"}, "headersType":"Form", "uri":{"path":"localhost:8080/addressbook/rest/contacts/get_all", "query":{"delimiter":"&", "items":[{"enabled":true, "name":"account_id", "value":"1"}]}, "scheme":{"name":"http", "version":"V11"}}, "parentId":"F7165F8B-221B-4B45-B55E-7DDBAFCF1908"},{"uriEditor":true, "id":"AA92EB1F-1992-4122-8CB1-FF3D634EEFD0", "lastModified":"2016-04-12T11:27:05.124+03:00", "name":"Get all by tag and account (GET)", "headers":[{"enabled":true, "name":"Content-Type", "value":"application/json"}], "type":"Request", "method":{"link":"http://tools.ietf.org/html/rfc7231#section-4.3.1", "name":"GET"}, "body":{"autoSetLength":true, "textBody":"{\n  \"firstName\":\"Ivan\",\n  \"lastName\":\"Petrov\",\n  \"description\":\"demo entry\"\n}", "bodyType":"Text"}, "headersType":"Form", "uri":{"path":"localhost:8080/addressbook/rest/contacts/get_by_tag", "query":{"delimiter":"&", "items":[{"enabled":true, "name":"account_id", "value":"1"},{"enabled":true, "name":"tag_id", "value":"1"}]}, "scheme":{"name":"http", "version":"V11"}}, "parentId":"F7165F8B-221B-4B45-B55E-7DDBAFCF1908"},{"uriEditor":true, "id":"5C41B854-7C74-418D-BDB9-97975C28D089", "lastModified":"2016-04-03T15:46:05.806+03:00", "name":"Read (GET)", "headers":[], "type":"Request", "method":{"link":"http://tools.ietf.org/html/rfc7231#section-4.3.1", "name":"GET"}, "body":{"autoSetLength":true, "bodyType":"Text"}, "headersType":"Form", "uri":{"path":"localhost:8080/addressbook/rest/contacts/15", "query":{"delimiter":"&", "items":[]}, "scheme":{"name":"http", "version":"V11"}}, "parentId":"F7165F8B-221B-4B45-B55E-7DDBAFCF1908"},{"uriEditor":true, "id":"D8AF351A-6350-452C-906F-342F5B202F45", "lastModified":"2016-04-03T15:47:34.702+03:00", "name":"Update (PUT)", "headers":[{"enabled":true, "name":"Content-Type", "value":"application/json"}], "type":"Request", "method":{"requestBody":true, "link":"http://tools.ietf.org/html/rfc7231#section-4.3.4", "name":"PUT"}, "body":{"autoSetLength":true, "textBody":"{\n  \"firstName\":\"Alexey\",\n  \"lastName\":\"Ivanov\"\n}", "bodyType":"Text"}, "headersType":"Form", "uri":{"path":"localhost:8080/addressbook/rest/contacts/15", "query":{"delimiter":"&", "items":[]}, "scheme":{"name":"http", "version":"V11"}}, "parentId":"F7165F8B-221B-4B45-B55E-7DDBAFCF1908"},{"uriEditor":true, "id":"8D1FA2EB-B964-4FCD-984D-9BDD3375F974", "lastModified":"2016-04-03T16:12:56.128+03:00", "name":"Create (POST)", "headers":[{"enabled":true, "name":"Content-Type", "value":"application/json"}], "type":"Request", "method":{"requestBody":true, "link":"http://tools.ietf.org/html/rfc7231#section-4.3.3", "name":"POST"}, "body":{"autoSetLength":true, "textBody":"{\n  \"typeName\":\"Wow! Works\" \n}", "bodyType":"Text"}, "headersType":"Form", "uri":{"path":"localhost:8080/addressbook/rest/field_types", "query":{"delimiter":"&", "items":[]}, "scheme":{"name":"http", "version":"V11"}}, "parentId":"AD727C77-C632-4F8B-915B-D96A4FFDCBC6"},{"uriEditor":true, "id":"14E08E82-94CC-400A-8031-59EE50AF424F", "lastModified":"2016-03-26T21:50:10.083+03:00", "name":"Delete (DELETE)", "headers":[], "type":"Request", "method":{"link":"http://tools.ietf.org/html/rfc7231#section-4.3.5", "name":"DELETE"}, "body":{"autoSetLength":true, "bodyType":"Text"}, "headersType":"Form", "uri":{"path":"localhost:8080/addressbook/rest/field_types/1", "query":{"delimiter":"&", "items":[]}, "scheme":{"name":"http", "version":"V11"}}, "parentId":"AD727C77-C632-4F8B-915B-D96A4FFDCBC6"},{"uriEditor":true, "id":"78760B05-B8CF-44E7-AAC6-2DB3684730BE", "lastModified":"2016-03-26T21:48:48.272+03:00", "name":"Read (GET)", "headers":[], "type":"Request", "method":{"link":"http://tools.ietf.org/html/rfc7231#section-4.3.1", "name":"GET"}, "body":{"autoSetLength":true, "bodyType":"Text"}, "headersType":"Form", "uri":{"path":"localhost:8080/addressbook/rest/field_types/1", "query":{"delimiter":"&", "items":[]}, "scheme":{"name":"http", "version":"V11"}}, "parentId":"AD727C77-C632-4F8B-915B-D96A4FFDCBC6"},{"uriEditor":true, "id":"A191F459-E438-4958-B590-FF5F5959F305", "lastModified":"2016-04-03T16:13:38.303+03:00", "name":"Update (PUT)", "headers":[{"enabled":true, "name":"Content-Type", "value":"application/json"}], "type":"Request", "method":{"requestBody":true, "link":"http://tools.ietf.org/html/rfc7231#section-4.3.4", "name":"PUT"}, "body":{"autoSetLength":true, "textBody":"{\n  \"typeName\":\"updatedName\"\n}", "bodyType":"Text"}, "headersType":"Form", "uri":{"path":"localhost:8080/addressbook/rest/field_types/17", "query":{"delimiter":"&", "items":[]}, "scheme":{"name":"http", "version":"V11"}}, "parentId":"AD727C77-C632-4F8B-915B-D96A4FFDCBC6"},{"uriEditor":true, "id":"53A7F375-0B40-412A-9A26-704C7B97603A", "lastModified":"2016-04-06T00:06:21.226+03:00", "name":"Create (POST)", "headers":[{"enabled":true, "name":"Content-Type", "value":"application/json"}], "type":"Request", "method":{"requestBody":true, "link":"http://tools.ietf.org/html/rfc7231#section-4.3.3", "name":"POST"}, "body":{"autoSetLength":true, "textBody":"{\n  \"date\":\"2012-04-23\",\n  \"value\":\"www\"\n}", "bodyType":"Text"}, "headersType":"Form", "uri":{"path":"localhost:8080/addressbook/rest/notes", "query":{"delimiter":"&", "items":[{"enabled":true, "name":"person_id", "value":"1"}]}, "scheme":{"name":"http", "version":"V11"}}, "parentId":"6F0D603A-0EE4-44C8-ADB9-66EFA5ECD7FF"},{"uriEditor":true, "id":"22734E03-EF68-4AF7-A708-4976F08FDAB6", "lastModified":"2016-03-26T21:21:01.405+03:00", "name":"Delete (DELETE)", "headers":[], "type":"Request", "method":{"link":"http://tools.ietf.org/html/rfc7231#section-4.3.5", "name":"DELETE"}, "body":{"autoSetLength":true, "bodyType":"Text"}, "headersType":"Form", "uri":{"path":"localhost:8080/addressbook/rest/notes/1", "query":{"delimiter":"&", "items":[]}, "scheme":{"name":"http", "version":"V11"}}, "parentId":"6F0D603A-0EE4-44C8-ADB9-66EFA5ECD7FF"},{"uriEditor":true, "id":"9C4895B8-5816-43FD-A9AF-6F45B7CC217A", "lastModified":"2016-04-12T12:24:39.304+03:00", "name":"Get all by person (GET)", "headers":[], "type":"Request", "method":{"link":"http://tools.ietf.org/html/rfc7231#section-4.3.1", "name":"GET"}, "body":{"autoSetLength":true, "bodyType":"Text"}, "headersType":"Form", "uri":{"path":"localhost:8080/addressbook/rest/notes/get_by_person", "query":{"delimiter":"&", "items":[{"enabled":true, "name":"person_id", "value":"256"}]}, "scheme":{"name":"http", "version":"V11"}}, "parentId":"6F0D603A-0EE4-44C8-ADB9-66EFA5ECD7FF"},{"uriEditor":true, "id":"27A3937B-BB05-43C3-BC33-5023D69AD903", "lastModified":"2016-03-26T21:20:13.770+03:00", "name":"Read (GET)", "headers":[], "type":"Request", "method":{"link":"http://tools.ietf.org/html/rfc7231#section-4.3.1", "name":"GET"}, "body":{"autoSetLength":true, "bodyType":"Text"}, "headersType":"Form", "uri":{"path":"localhost:8080/addressbook/rest/notes/1", "query":{"delimiter":"&", "items":[]}, "scheme":{"name":"http", "version":"V11"}}, "parentId":"6F0D603A-0EE4-44C8-ADB9-66EFA5ECD7FF"},{"uriEditor":true, "id":"1F929B24-5F04-4E86-B472-388B08E6B27F", "lastModified":"2016-04-09T13:50:42.127+03:00", "name":"Update (PUT)", "headers":[{"enabled":true, "name":"Content-Type", "value":"application/json"}], "type":"Request", "method":{"requestBody":true, "link":"http://tools.ietf.org/html/rfc7231#section-4.3.4", "name":"PUT"}, "body":{"autoSetLength":true, "textBody":"{\n  \"date\":\"1999-03-15\",\n  \"value\":\"new_value\"\n}", "bodyType":"Text"}, "headersType":"Form", "uri":{"path":"localhost:8080/addressbook/rest/notes/18", "query":{"delimiter":"&", "items":[{"enabled":true, "name":"person_id", "value":"1"}]}, "scheme":{"name":"http", "version":"V11"}}, "parentId":"6F0D603A-0EE4-44C8-ADB9-66EFA5ECD7FF"},{"uriEditor":true, "id":"45B57AF0-B4EC-4BFC-8602-E4C287F4C8E8", "lastModified":"2016-03-30T19:18:15.748+03:00", "name":"Create (POST)", "headers":[{"enabled":true, "name":"Content-Type", "value":"application/json"}], "type":"Request", "method":{"requestBody":true, "link":"http://tools.ietf.org/html/rfc7231#section-4.3.3", "name":"POST"}, "body":{"autoSetLength":true, "textBody":"", "bodyType":"Text"}, "headersType":"Form", "uri":{"path":"localhost:8080/addressbook/rest/permissions", "query":{"delimiter":"&", "items":[]}, "scheme":{"name":"http", "version":"V11"}}, "parentId":"7B6D9782-182B-4D95-84D9-7E8304262F77"},{"uriEditor":true, "id":"1B4304C5-5B13-4DF2-B698-3D5569997025", "lastModified":"2016-03-26T21:41:06.751+03:00", "name":"Delete (DELETE)", "headers":[], "type":"Request", "method":{"link":"http://tools.ietf.org/html/rfc7231#section-4.3.5", "name":"DELETE"}, "body":{"autoSetLength":true, "bodyType":"Text"}, "headersType":"Form", "uri":{"path":"localhost:8080/addressbook/rest/permissions/1", "query":{"delimiter":"&", "items":[]}, "scheme":{"name":"http", "version":"V11"}}, "parentId":"7B6D9782-182B-4D95-84D9-7E8304262F77"},{"uriEditor":true, "id":"06753AA6-0DCE-441D-BDC5-2F20581B6C09", "lastModified":"2016-03-26T21:40:04.760+03:00", "name":"Read (GET)", "headers":[], "type":"Request", "method":{"link":"http://tools.ietf.org/html/rfc7231#section-4.3.1", "name":"GET"}, "body":{"autoSetLength":true, "bodyType":"Text"}, "headersType":"Form", "uri":{"path":"localhost:8080/addressbook/rest/permissions/1", "query":{"delimiter":"&", "items":[]}, "scheme":{"name":"http", "version":"V11"}}, "parentId":"7B6D9782-182B-4D95-84D9-7E8304262F77"},{"uriEditor":true, "id":"24881B98-6660-4074-809C-FAB0DA65D235", "lastModified":"2016-03-30T19:18:24.675+03:00", "name":"Update (PUT)", "headers":[{"enabled":true, "name":"Content-Type", "value":"application/json"}], "type":"Request", "method":{"requestBody":true, "link":"http://tools.ietf.org/html/rfc7231#section-4.3.4", "name":"PUT"}, "body":{"autoSetLength":true, "textBody":"", "bodyType":"Text"}, "headersType":"Form", "uri":{"path":"localhost:8080/addressbook/rest/permissions/1", "query":{"delimiter":"&", "items":[]}, "scheme":{"name":"http", "version":"V11"}}, "parentId":"7B6D9782-182B-4D95-84D9-7E8304262F77"},{"uriEditor":true, "id":"66471EA3-2582-4470-80E6-F9734AF6E6FB", "lastModified":"2016-03-30T19:18:34.095+03:00", "name":"Create (POST)", "headers":[{"enabled":true, "name":"Content-Type", "value":"application/json"}], "type":"Request", "method":{"requestBody":true, "link":"http://tools.ietf.org/html/rfc7231#section-4.3.3", "name":"POST"}, "body":{"autoSetLength":true, "textBody":"", "bodyType":"Text"}, "headersType":"Form", "uri":{"path":"localhost:8080/addressbook/rest/roles", "query":{"delimiter":"&", "items":[]}, "scheme":{"name":"http", "version":"V11"}}, "parentId":"55472F2F-E41F-4A8A-8814-1AF4D6CFAEE5"},{"uriEditor":true, "id":"E0F4DFC6-6F5D-4EBD-8145-407BA0FFDF2B", "lastModified":"2016-03-26T21:38:31.009+03:00", "name":"Delete (DELETE)", "headers":[], "type":"Request", "method":{"link":"http://tools.ietf.org/html/rfc7231#section-4.3.5", "name":"DELETE"}, "body":{"autoSetLength":true, "bodyType":"Text"}, "headersType":"Form", "uri":{"path":"localhost:8080/addressbook/rest/roles/1", "query":{"delimiter":"&", "items":[]}, "scheme":{"name":"http", "version":"V11"}}, "parentId":"55472F2F-E41F-4A8A-8814-1AF4D6CFAEE5"},{"uriEditor":true, "id":"42C96F7C-4E57-4368-B91D-D9462F5E3E23", "lastModified":"2016-03-26T21:37:27.285+03:00", "name":"Read (GET)", "headers":[], "type":"Request", "method":{"link":"http://tools.ietf.org/html/rfc7231#section-4.3.1", "name":"GET"}, "body":{"autoSetLength":true, "bodyType":"Text"}, "headersType":"Form", "uri":{"path":"localhost:8080/addressbook/rest/roles/1", "query":{"delimiter":"&", "items":[]}, "scheme":{"name":"http", "version":"V11"}}, "parentId":"55472F2F-E41F-4A8A-8814-1AF4D6CFAEE5"},{"uriEditor":true, "id":"5C814A32-FA74-4514-A697-31C1130BCB97", "lastModified":"2016-03-30T19:18:54.574+03:00", "name":"Update (PUT)", "headers":[{"enabled":true, "name":"Content-Type", "value":"application/json"}], "type":"Request", "method":{"requestBody":true, "link":"http://tools.ietf.org/html/rfc7231#section-4.3.4", "name":"PUT"}, "body":{"autoSetLength":true, "textBody":"", "bodyType":"Text"}, "headersType":"Form", "uri":{"path":"localhost:8080/addressbook/rest/roles/1", "query":{"delimiter":"&", "items":[]}, "scheme":{"name":"http", "version":"V11"}}, "parentId":"55472F2F-E41F-4A8A-8814-1AF4D6CFAEE5"},{"uriEditor":true, "id":"E7EDDFA0-5836-402B-B16C-E3F8C0DFCD81", "lastModified":"2016-04-03T15:57:10.619+03:00", "name":"Create (POST)", "headers":[{"enabled":true, "name":"Content-Type", "value":"application/json"}], "type":"Request", "method":{"requestBody":true, "link":"http://tools.ietf.org/html/rfc7231#section-4.3.3", "name":"POST"}, "body":{"autoSetLength":true, "textBody":"{\n  \"name\":\"hello\",\n  \"description\":\"world\"\n}", "bodyType":"Text"}, "headersType":"Form", "uri":{"path":"localhost:8080/addressbook/rest/tags", "query":{"delimiter":"&", "items":[]}, "scheme":{"name":"http", "version":"V11"}}, "parentId":"16087174-6DB1-4B0C-8CEC-749D79440158"},{"uriEditor":true, "id":"11C1B3D5-B5ED-41A5-8EBD-A262FA78315F", "lastModified":"2016-03-26T21:18:33.524+03:00", "name":"Delete (DELETE)", "headers":[], "type":"Request", "method":{"link":"http://tools.ietf.org/html/rfc7231#section-4.3.5", "name":"DELETE"}, "body":{"autoSetLength":true, "bodyType":"Text"}, "headersType":"Form", "uri":{"path":"localhost:8080/addressbook/rest/tags/1", "query":{"delimiter":"&", "items":[]}, "scheme":{"name":"http", "version":"V11"}}, "parentId":"16087174-6DB1-4B0C-8CEC-749D79440158"},{"uriEditor":true, "id":"51E4CA88-179A-42D7-AA51-DD89B974D021", "lastModified":"2016-04-12T12:00:27.568+03:00", "name":"Get all by account (GET)", "headers":[{"enabled":true, "name":"Content-Type", "value":"application/json"}], "type":"Request", "method":{"link":"http://tools.ietf.org/html/rfc7231#section-4.3.1", "name":"GET"}, "body":{"autoSetLength":true, "textBody":"{\n  \"name\":\"hello\",\n  \"description\":\"world\"\n}", "bodyType":"Text"}, "headersType":"Form", "uri":{"path":"localhost:8080/addressbook/rest/tags/get_all", "query":{"delimiter":"&", "items":[{"enabled":true, "name":"account_id", "value":"1"}]}, "scheme":{"name":"http", "version":"V11"}}, "parentId":"16087174-6DB1-4B0C-8CEC-749D79440158"},{"uriEditor":true, "id":"29939CC4-55C0-4F53-9734-B1F8213A0048", "lastModified":"2016-03-26T21:17:31.299+03:00", "name":"Read (GET)", "headers":[], "type":"Request", "method":{"link":"http://tools.ietf.org/html/rfc7231#section-4.3.1", "name":"GET"}, "body":{"autoSetLength":true, "bodyType":"Text"}, "headersType":"Form", "uri":{"path":"localhost:8080/addressbook/rest/tags/1", "query":{"delimiter":"&", "items":[]}, "scheme":{"name":"http", "version":"V11"}}, "parentId":"16087174-6DB1-4B0C-8CEC-749D79440158"},{"uriEditor":true, "id":"CB8D3350-7B9A-46AB-B7C9-A5F0EF469A84", "lastModified":"2016-04-03T16:02:33.781+03:00", "name":"Update (PUT)", "headers":[{"enabled":true, "name":"Content-Type", "value":"application/json"}], "type":"Request", "method":{"requestBody":true, "link":"http://tools.ietf.org/html/rfc7231#section-4.3.4", "name":"PUT"}, "body":{"autoSetLength":true, "textBody":"{\n  \"name\":\"Qwerty\",\n  \"description\":\"ddd\"\n}", "bodyType":"Text"}, "headersType":"Form", "uri":{"path":"localhost:8080/addressbook/rest/tags/16", "query":{"delimiter":"&", "items":[]}, "scheme":{"name":"http", "version":"V11"}}, "parentId":"16087174-6DB1-4B0C-8CEC-749D79440158"},{"uriEditor":true, "id":"076F9534-C9B4-4EA1-AD9D-2ABCD67B2238", "lastModified":"2016-03-28T11:40:34.950+03:00", "name":"Get from test table", "headers":[], "type":"Request", "method":{"link":"http://tools.ietf.org/html/rfc7231#section-4.3.1", "name":"GET"}, "body":{"autoSetLength":true, "textBody":"{\n  \"description\":\"hellotest-(post)\"\n}", "bodyType":"Text"}, "headersType":"Form", "uri":{"path":"localhost:8080/addressbook/rest/test/performance/get", "query":{"delimiter":"&", "items":[]}, "scheme":{"name":"http", "version":"V11"}}, "parentId":"9E23650C-0AF1-46AC-BB73-298F906D1008"},{"uriEditor":true, "id":"2716510C-812A-41FC-9AEF-1F8D1940F42D", "lastModified":"2016-03-28T11:40:44.444+03:00", "name":"Insert to test table (POST)", "headers":[{"enabled":true, "name":"Content-Type", "value":"application/json"}], "type":"Request", "method":{"requestBody":true, "link":"http://tools.ietf.org/html/rfc7231#section-4.3.3", "name":"POST"}, "body":{"autoSetLength":true, "textBody":"{\n  \"description\":\"hellotest-(post)\"\n}", "bodyType":"Text"}, "headersType":"Form", "uri":{"path":"localhost:8080/addressbook/rest/test/performance/insert/", "query":{"delimiter":"&", "items":[]}, "scheme":{"name":"http", "version":"V11"}}, "parentId":"9E23650C-0AF1-46AC-BB73-298F906D1008"},{"uriEditor":true, "id":"32F0FFA3-84F9-4E9C-96F7-4580A12C9E8B", "lastModified":"2016-03-28T11:40:53.621+03:00", "name":"Insert to test table (PUT)", "headers":[], "type":"Request", "method":{"requestBody":true, "link":"http://tools.ietf.org/html/rfc7231#section-4.3.4", "name":"PUT"}, "body":{"autoSetLength":true, "textBody":"", "bodyType":"Text"}, "headersType":"Form", "uri":{"path":"localhost:8080/addressbook/rest/test/performance/insert/hellotest", "query":{"delimiter":"&", "items":[]}, "scheme":{"name":"http", "version":"V11"}}, "parentId":"9E23650C-0AF1-46AC-BB73-298F906D1008"},{"uriEditor":true, "id":"4DC93470-9F44-4009-8213-A6D2B5DD17A8", "lastModified":"2016-03-28T11:41:02.313+03:00", "name":"Simple test", "headers":[], "type":"Request", "method":{"link":"http://tools.ietf.org/html/rfc7231#section-4.3.1", "name":"GET"}, "body":{"autoSetLength":true, "textBody":"{\n  \"description\":\"hellotest-(post)\"\n}", "bodyType":"Text"}, "headersType":"Form", "uri":{"path":"localhost:8080/addressbook/rest/test/performance/simple", "query":{"delimiter":"&", "items":[]}, "scheme":{"name":"http", "version":"V11"}}, "parentId":"9E23650C-0AF1-46AC-BB73-298F906D1008"},{"uriEditor":true, "id":"8D5AFECB-9004-465B-A875-B67FA51E800F", "lastModified":"2016-03-26T16:45:53.503+03:00", "name":"Get users by role", "headers":[], "type":"Request", "method":{"link":"http://tools.ietf.org/html/rfc7231#section-4.3.1", "name":"GET"}, "body":{"autoSetLength":true, "textBody":"{\n  \"description\":\"hellotest-(post)\"\n}", "bodyType":"Text"}, "headersType":"Form", "uri":{"path":"localhost:8080/addressbook/rest/accounts/getAllByRole", "query":{"delimiter":"&", "items":[{"enabled":true, "name":"role", "value":"User"}]}, "scheme":{"name":"http", "version":"V11"}}, "parentId":"6A685804-264A-45FA-9932-691E9313130F"}]}